setup.py
distributions_S97/Binomialdistribution.py
distributions_S97/Gaussiandistribution.py
distributions_S97/Generaldistribution.py
distributions_S97/__init__.py
distributions_S97.egg-info/PKG-INFO
distributions_S97.egg-info/SOURCES.txt
distributions_S97.egg-info/dependency_links.txt
distributions_S97.egg-info/not-zip-safe
distributions_S97.egg-info/top_level.txt