Metadata-Version: 1.0
Name: distributions-S97
Version: 0.2
Summary: Gaussian and Boolean distributions
Home-page: UNKNOWN
Author: Salma Tarek
Author-email: UNKNOWN
License: UNKNOWN
Platform: UNKNOWN
